persim/__init__.py
persim/_version.py
persim/bottleneck.py
persim/gromov_hausdorff.py
persim/heat.py
persim/images.py
persim/images_kernels.py
persim/images_weights.py
persim/persistent_entropy.py
persim/sliced_wasserstein.py
persim/visuals.py
persim/wasserstein.py
persim/landscapes/__init__.py
persim/landscapes/approximate.py
persim/landscapes/auxiliary.py
persim/landscapes/base.py
persim/landscapes/exact.py
persim/landscapes/tools.py
persim/landscapes/transformer.py
persim/landscapes/visuals.py
persim-0.3.5.dist-info/LICENSE.txt
persim-0.3.5.dist-info/METADATA
persim-0.3.5.dist-info/WHEEL
persim-0.3.5.dist-info/top_level.txt
persim-0.3.5.dist-info/RECORD
