Metadata-Version: 2.1
Name: persim
Version: 0.3.5
Summary: Distances and representations of persistence diagrams
Home-page: https://persim.scikit-tda.org
Author: Nathaniel Saul, Chris Tralie, Francis Motta, Michael Catanzaro, Gabrielle Angeloro, Calder Sheagren
Author-email: nat@riverasaul.com, chris.tralie@gmail.com, francis.c.motta@gmail.com, catanzaromj@gmail.com, gabrielleangeloro@gmail.com, caldersheagren@gmail.com
License: MIT
Keywords: persistent homology,persistence images,persistence diagrams,topological data analysis,algebraic topology,unsupervised learning,supervised learning,machine learning,sliced wasserstein distance,bottleneck distance
Classifier: Development Status :: 3 - Alpha
Classifier: Intended Audience :: Science/Research
Classifier: Intended Audience :: Education
Classifier: Intended Audience :: Financial and Insurance Industry
Classifier: Intended Audience :: Healthcare Industry
Classifier: Topic :: Scientific/Engineering :: Information Analysis
Classifier: Topic :: Scientific/Engineering :: Mathematics
Classifier: License :: OSI Approved :: MIT License
Classifier: Programming Language :: Python :: 3.6
Classifier: Programming Language :: Python :: 3.7
Classifier: Programming Language :: Python :: 3.8
Requires-Python: >=3.6
License-File: LICENSE.txt
Requires-Dist: scikit-learn
Requires-Dist: numpy
Requires-Dist: matplotlib
Requires-Dist: scipy
Requires-Dist: hopcroftkarp
Requires-Dist: deprecated
Requires-Dist: joblib
Provides-Extra: docs
Requires-Dist: sktda-docs-config ; extra == 'docs'
Provides-Extra: testing
Requires-Dist: pytest ; extra == 'testing'
Requires-Dist: pytest-cov ; extra == 'testing'
